{"visible": {"type": 0, "list_id": 0}, "created_at": "Thu Apr 25 20:09:56 +0800 2024", "id": 5027139826745664, "idstr": "5027139826745664", "mid": "5027139826745664", "mblogid": "Obo1UsiR2", "user": {"id": 1829429131, "idstr": "1829429131", "pc_new": 6, "screen_name": "小憩_nica", "profile_image_url": "https://tvax2.sinaimg.cn/crop.0.0.750.750.50/6d0adf8bly8fhbh2xeu7vj20ku0kvjsq.jpg?KID=imgbed,tva&amp;Expires=1715077963&amp;ssig=uOFcSpye7g", "profile_url": "/u/1829429131", "verified": true, "verified_type": 0, "domain": "", "weihao": "", "verified_type_ext": 0, "avatar_large": "https://tvax2.sinaimg.cn/crop.0.0.750.750.180/6d0adf8bly8fhbh2xeu7vj20ku0kvjsq.jpg?KID=imgbed,tva&amp;Expires=1715077963&amp;ssig=F8sFuq2fh6", "avatar_hd": "https://tvax2.sinaimg.cn/crop.0.0.750.750.1024/6d0adf8bly8fhbh2xeu7vj20ku0kvjsq.jpg?KID=imgbed,tva&amp;Expires=1715077963&amp;ssig=EyWKkV4r1a", "follow_me": false, "following": false, "mbrank": 7, "mbtype": 12, "v_plus": 0, "planet_video": false, "icon_list": [{"type": "vip", "data": {"mbrank": 7, "mbtype": 12, "svip": 0, "vvip": 0}}]}, "can_edit": false, "text_raw": "上下都宽松，很舒服，还带点小精致[心] ​​​", "textLength": 36, "annotations": [{"photo_sub_type": "0,0,0"}, {"client_mblogid": "iPhone-036FF7A1-C3E8-41F5-AEC8-798553BA0148"}, {"source_text": "", "phone_id": ""}, {"mapi_request": true}], "source": "iPhone 12 Pro Max", "favorited": false, "rid": "0_0_0_5225628752756192080_0_0_0", "pic_ids": ["6d0adf8bgy1hp3c0ev3hzj229q30y4qq", "6d0adf8bgy1hp3c0hrl74j22c03404qq", "6d0adf8bgy1hp3c3llbvhj22c03401ky"], "pic_focus_point": [{"focus_point": {"left": 0.08070051, "top": 0.12812437, "width": 0.91929936, "height": 0.68947464}, "pic_id": "6d0adf8bgy1hp3c3llbvhj22c03401ky"}, {"focus_point": {"left": 0.4768116, "top": 0.110869564, "width": 0.123188406, "height": 0.12826087}, "pic_id": "6d0adf8bgy1hp3c0hrl74j22c03404qq"}, {"focus_point": {"left": 0.4985507, "top": 0.15434782, "width": 0.088405795, "height": 0.08369565}, "pic_id": "6d0adf8bgy1hp3c0ev3hzj229q30y4qq"}], "pic_num": 3, "pic_infos": {"6d0adf8bgy1hp3c0ev3hzj229q30y4qq": {"thumbnail": {"url": "https://wx1.sinaimg.cn/wap180/6d0adf8bgy1hp3c0ev3hzj229q30y4qq.jpg", "width": 135, "height": 180, "cut_type": 1, "type": null}, "bmiddle": {"url": "https://wx1.sinaimg.cn/wap360/6d0adf8bgy1hp3c0ev3hzj229q30y4qq.jpg", "width": 270, "height": 360, "cut_type": 1, "type": null}, "large": {"url": "https://wx1.sinaimg.cn/orj960/6d0adf8bgy1hp3c0ev3hzj229q30y4qq.jpg", "width": 960, "height": 1279, "cut_type": 1, "type": null}, "original": {"url": "https://wx1.sinaimg.cn/orj1080/6d0adf8bgy1hp3c0ev3hzj229q30y4qq.jpg", "width": 1080, "height": 1439, "cut_type": 1, "type": null}, "largest": {"url": "https://wx1.sinaimg.cn/large/6d0adf8bgy1hp3c0ev3hzj229q30y4qq.jpg", "width": 2048, "height": 2730, "cut_type": 1, "type": null}, "mw2000": {"url": "https://wx1.sinaimg.cn/mw2000/6d0adf8bgy1hp3c0ev3hzj229q30y4qq.jpg", "width": 2000, "height": 2666, "cut_type": 1, "type": null}, "largecover": {"url": "https://wx1.sinaimg.cn/cmw960/6d0adf8bgy1hp3c0ev3hzj229q30y4qq.jpg", "width": 960, "height": 1279, "cut_type": 1, "type": null}, "focus_point": {"left": 0.4985507, "top": 0.15434782, "width": 0.088405795, "height": 0.08369565}, "object_id": "1042018:4b7e7b252c425e4709c50d28e94a1deb", "pic_id": "6d0adf8bgy1hp3c0ev3hzj229q30y4qq", "photo_tag": 0, "type": "pic", "pic_status": 1}, "6d0adf8bgy1hp3c0hrl74j22c03404qq": {"thumbnail": {"url": "https://wx4.sinaimg.cn/wap180/6d0adf8bgy1hp3c0hrl74j22c03404qq.jpg", "width": 135, "height": 180, "cut_type": 1, "type": null}, "bmiddle": {"url": "https://wx4.sinaimg.cn/wap360/6d0adf8bgy1hp3c0hrl74j22c03404qq.jpg", "width": 270, "height": 360, "cut_type": 1, "type": null}, "large": {"url": "https://wx4.sinaimg.cn/orj960/6d0adf8bgy1hp3c0hrl74j22c03404qq.jpg", "width": 960, "height": 1279, "cut_type": 1, "type": null}, "original": {"url": "https://wx4.sinaimg.cn/orj1080/6d0adf8bgy1hp3c0hrl74j22c03404qq.jpg", "width": 1080, "height": 1439, "cut_type": 1, "type": null}, "largest": {"url": "https://wx4.sinaimg.cn/large/6d0adf8bgy1hp3c0hrl74j22c03404qq.jpg", "width": 2048, "height": 2730, "cut_type": 1, "type": null}, "mw2000": {"url": "https://wx4.sinaimg.cn/mw2000/6d0adf8bgy1hp3c0hrl74j22c03404qq.jpg", "width": 2000, "height": 2666, "cut_type": 1, "type": null}, "largecover": {"url": "https://wx4.sinaimg.cn/cmw960/6d0adf8bgy1hp3c0hrl74j22c03404qq.jpg", "width": 960, "height": 1279, "cut_type": 1, "type": null}, "focus_point": {"left": 0.4768116, "top": 0.110869564, "width": 0.123188406, "height": 0.12826087}, "object_id": "1042018:cb3649c623a381d71b6220962403375a", "pic_id": "6d0adf8bgy1hp3c0hrl74j22c03404qq", "photo_tag": 0, "type": "pic", "pic_status": 1}, "6d0adf8bgy1hp3c3llbvhj22c03401ky": {"thumbnail": {"url": "https://wx4.sinaimg.cn/wap180/6d0adf8bgy1hp3c3llbvhj22c03401ky.jpg", "width": 135, "height": 180, "cut_type": 1, "type": null}, "bmiddle": {"url": "https://wx4.sinaimg.cn/wap360/6d0adf8bgy1hp3c3llbvhj22c03401ky.jpg", "width": 270, "height": 360, "cut_type": 1, "type": null}, "large": {"url": "https://wx4.sinaimg.cn/orj960/6d0adf8bgy1hp3c3llbvhj22c03401ky.jpg", "width": 960, "height": 1279, "cut_type": 1, "type": null}, "original": {"url": "https://wx4.sinaimg.cn/orj1080/6d0adf8bgy1hp3c3llbvhj22c03401ky.jpg", "width": 1080, "height": 1439, "cut_type": 1, "type": null}, "largest": {"url": "https://wx4.sinaimg.cn/large/6d0adf8bgy1hp3c3llbvhj22c03401ky.jpg", "width": 2048, "height": 2730, "cut_type": 1, "type": null}, "mw2000": {"url": "https://wx4.sinaimg.cn/mw2000/6d0adf8bgy1hp3c3llbvhj22c03401ky.jpg", "width": 2000, "height": 2666, "cut_type": 1, "type": null}, "largecover": {"url": "https://wx4.sinaimg.cn/cmw960/6d0adf8bgy1hp3c3llbvhj22c03401ky.jpg", "width": 960, "height": 1279, "cut_type": 1, "type": null}, "focus_point": {"left": 0.08070051, "top": 0.12812437, "width": 0.91929936, "height": 0.68947464}, "object_id": "1042018:8344799c474298ba9f67e32fb4838e36", "pic_id": "6d0adf8bgy1hp3c3llbvhj22c03401ky", "photo_tag": 0, "type": "pic", "pic_status": 1}}, "is_paid": false, "mblog_vip_type": 0, "number_display_strategy": {"apply_scenario_flag": 3, "display_text_min_number": 1000000, "display_text": "100万+"}, "reposts_count": 1, "comments_count": 3, "attitudes_count": 15, "attitudes_status": 0, "isLongText": false, "mlevel": 0, "content_auth": 0, "is_show_bulletin": 2, "comment_manage_info": {"comment_permission_type": -1, "approval_comment_type": 0, "comment_sort_type": 0}, "share_repost_type": 0, "title": {"text": "公开", "base_color": 1, "icon_url": "http://h5.sinaimg.cn/upload/2015/07/14/34/timeline_title_public.png"}, "mblogtype": 0, "showFeedRepost": false, "showFeedComment": false, "pictureViewerSign": false, "showPictureViewer": false, "rcList": [], "text": "上下都宽松，很舒服，还带点小精致&lt;img alt=\"[心]\" title=\"[心]\" src=\"https://face.t.sinajs.cn/t4/appstyle/expression/ext/normal/8a/2018new_xin_org.png\" /&gt; ​​​", "region_name": "发布于 四川", "customIcons": [], "ok": 1}