{"visible": {"type": 0, "list_id": 0}, "created_at": "Fri Jul 28 14:44:18 +0800 2023", "id": 4928488375850047, "idstr": "4928488375850047", "mid": "4928488375850047", "mblogid": "NbX6ZoxRB", "user": {"id": 2072043652, "idstr": "2072043652", "pc_new": 7, "screen_name": "路边的羽毛", "profile_image_url": "https://tvax3.sinaimg.cn/crop.0.0.996.996.50/7b80e084ly8gu67521cnrj20ro0roabk.jpg?KID=imgbed,tva&amp;Expires=1714384199&amp;ssig=tjHlLwz1At", "profile_url": "/u/2072043652", "verified": false, "verified_type": -1, "domain": "", "weihao": "", "avatar_large": "https://tvax3.sinaimg.cn/crop.0.0.996.996.180/7b80e084ly8gu67521cnrj20ro0roabk.jpg?KID=imgbed,tva&amp;Expires=1714384199&amp;ssig=6birotSkso", "avatar_hd": "https://tvax3.sinaimg.cn/crop.0.0.996.996.1024/7b80e084ly8gu67521cnrj20ro0roabk.jpg?KID=imgbed,tva&amp;Expires=1714384199&amp;ssig=3Ml1NM9RLn", "follow_me": false, "following": false, "mbrank": 0, "mbtype": 0, "v_plus": 0, "planet_video": true, "icon_list": []}, "can_edit": false, "text_raw": "分享图片 ​​​", "textLength": 8, "annotations": [{"photo_sub_type": "0"}, [], {"client_mblogid": "iPhone-5853C05F-57F5-4B24-A0F3-EF1D2DCD5AB5"}, {"source_text": "", "phone_id": ""}, {"mapi_request": true}], "source": "iPhone客户端", "favorited": false, "rid": "0_0_0_164174703987679645_0_0_0", "pic_ids": ["7b80e084ly1hgcm6keg4aj20zu0s3ju7"], "pic_num": 1, "pic_infos": {"7b80e084ly1hgcm6keg4aj20zu0s3ju7": {"thumbnail": {"url": "https://wx3.sinaimg.cn/wap180/7b80e084ly1hgcm6keg4aj20zu0s3ju7.jpg", "width": 180, "height": 140, "cut_type": 1, "type": null}, "bmiddle": {"url": "https://wx3.sinaimg.cn/wap360/7b80e084ly1hgcm6keg4aj20zu0s3ju7.jpg", "width": 360, "height": 281, "cut_type": 1, "type": null}, "large": {"url": "https://wx3.sinaimg.cn/orj960/7b80e084ly1hgcm6keg4aj20zu0s3ju7.jpg", "width": 1224, "height": 960, "cut_type": 1, "type": null}, "original": {"url": "https://wx3.sinaimg.cn/orj1080/7b80e084ly1hgcm6keg4aj20zu0s3ju7.jpg", "width": 1290, "height": 1011, "cut_type": 1, "type": null}, "largest": {"url": "https://wx3.sinaimg.cn/large/7b80e084ly1hgcm6keg4aj20zu0s3ju7.jpg", "width": 1290, "height": 1011, "cut_type": 1, "type": null}, "mw2000": {"url": "https://wx3.sinaimg.cn/mw2000/7b80e084ly1hgcm6keg4aj20zu0s3ju7.jpg", "width": 1290, "height": 1011, "cut_type": 1, "type": null}, "largecover": {"url": "https://wx3.sinaimg.cn/cmw960/7b80e084ly1hgcm6keg4aj20zu0s3ju7.jpg", "width": 1224, "height": 960, "cut_type": 1, "type": null}, "object_id": "1042018:781b214313c2caa100fc94cc3fe094da", "pic_id": "7b80e084ly1hgcm6keg4aj20zu0s3ju7", "photo_tag": 0, "type": "pic", "pic_status": 0}}, "is_paid": false, "mblog_vip_type": 0, "number_display_strategy": {"apply_scenario_flag": 3, "display_text_min_number": 1000000, "display_text": "100万+"}, "reposts_count": 0, "comments_count": 0, "attitudes_count": 26, "attitudes_status": 0, "isLongText": false, "mlevel": 128, "complaint": {"showcontent": "此内容为不实消息，已处理。", "color": 1, "url": "http://service.account.weibo.com/show?rid=K1CeK8w9f664l", "actionlog": {"act_code": 6528, "fid": null, "lfid": null, "uicode": null, "luicode": null, "ext": "uid:2072043652|mid:4928488375850047|mlevel:128"}}, "content_auth": 0, "is_show_bulletin": 2, "comment_manage_info": {"comment_permission_type": -1, "approval_comment_type": 0, "comment_sort_type": 0}, "share_repost_type": 0, "title": {"text": "公开", "base_color": 1, "icon_url": "http://h5.sinaimg.cn/upload/2015/07/14/34/timeline_title_public.png"}, "mblogtype": 0, "showFeedRepost": false, "showFeedComment": false, "pictureViewerSign": false, "showPictureViewer": false, "rcList": [], "text": "分享图片 ​​​", "region_name": "发布于 安徽", "customIcons": [], "ok": 1, "proof": "经查，该微博称“泉州海峡体育中心被台风吹倒”不实，官方回应：体育场只是顶棚外部的少量彩板表皮脱落，主体结构完好。详情：https://weibo.com/1720962692/NbWwFpBVH。被投诉人言论构成“发布不实信息”，现根据《微博投诉操作细则》（https://service.account.weibo.com/roles/xize）第八章，对被举报人处理如下：扣除信用历史分10分。上述处理在公布后60分钟内生效。"}