{"visible": {"type": 0, "list_id": 0}, "created_at": "Sun Jul 09 14:39:32 +0800 2023", "id": 4921601806829078, "idstr": "4921601806829078", "mid": "4921601806829078", "mblogid": "N93XCsEyq", "user": {"id": 7766225324, "idstr": "7766225324", "pc_new": 0, "screen_name": "桂澜路七号", "profile_image_url": "https://tvax3.sinaimg.cn/crop.0.0.1080.1080.50/008tAhYMly8hfrnd7skqsj30u00u0q59.jpg?KID=imgbed,tva&amp;Expires=1714377602&amp;ssig=SOCEcuJX%2BG", "profile_url": "/u/7766225324", "verified": false, "verified_type": -1, "domain": "", "weihao": "", "avatar_large": "https://tvax3.sinaimg.cn/crop.0.0.1080.1080.180/008tAhYMly8hfrnd7skqsj30u00u0q59.jpg?KID=imgbed,tva&amp;Expires=1714377602&amp;ssig=1k5ugR3qtZ", "avatar_hd": "https://tvax3.sinaimg.cn/crop.0.0.1080.1080.1024/008tAhYMly8hfrnd7skqsj30u00u0q59.jpg?KID=imgbed,tva&amp;Expires=1714377602&amp;ssig=bhC5CtFmQy", "follow_me": false, "following": false, "mbrank": 0, "mbtype": 0, "v_plus": 0, "planet_video": false, "icon_list": []}, "can_edit": false, "text_raw": "发财的机会来了，本年度最佳风口！一夜暴富的机会！  ​​​", "textLength": 69, "annotations": [{"photo_sub_type": "0"}, [], {"spot_type": "0"}, {"place": {"poiid": "B2094252D164A2F9479F", "title": "胡桃里音乐酒馆(郑州上悦城购物中心店)", "type": "checkin", "spot_type": "0"}, "client_mblogid": "a3371b8c-9d93-49d0-97b2-2ec90325e9ac"}, {"source_text": "", "phone_id": ""}, {"mapi_request": true}], "source": "&lt;a target=\"_blank\" href=\"https://app.weibo.com/t/feed/5ovRO0\" rel=\"nofollow\"&gt;Redmi Note 12 Turbo&lt;/a&gt;", "favorited": false, "rid": "0_0_0_4867853097918779691_0_0_0", "pic_ids": ["008tAhYMly1hfqn94gq7zj30u0140grh"], "geo": {"type": "Point", "coordinates": [34.746414, 113.71625], "detail": {"poiid": "B2094252D164A2F9479F", "title": "胡桃里音乐酒馆(郑州上悦城购物中心店)", "type": "checkin", "spot_type": "0"}}, "pic_num": 1, "pic_infos": {"008tAhYMly1hfqn94gq7zj30u0140grh": {"thumbnail": {"url": "https://wx1.sinaimg.cn/wap180/008tAhYMly1hfqn94gq7zj30u0140grh.jpg", "width": 135, "height": 180, "cut_type": 1, "type": null}, "bmiddle": {"url": "https://wx1.sinaimg.cn/wap360/008tAhYMly1hfqn94gq7zj30u0140grh.jpg", "width": 270, "height": 360, "cut_type": 1, "type": null}, "large": {"url": "https://wx1.sinaimg.cn/orj960/008tAhYMly1hfqn94gq7zj30u0140grh.jpg", "width": 960, "height": 1280, "cut_type": 1, "type": null}, "original": {"url": "https://wx1.sinaimg.cn/orj1080/008tAhYMly1hfqn94gq7zj30u0140grh.jpg", "width": 1080, "height": 1440, "cut_type": 1, "type": null}, "largest": {"url": "https://wx1.sinaimg.cn/large/008tAhYMly1hfqn94gq7zj30u0140grh.jpg", "width": 1080, "height": 1440, "cut_type": 1, "type": null}, "mw2000": {"url": "https://wx1.sinaimg.cn/mw2000/008tAhYMly1hfqn94gq7zj30u0140grh.jpg", "width": 1080, "height": 1440, "cut_type": 1, "type": null}, "largecover": {"url": "https://wx1.sinaimg.cn/cmw960/008tAhYMly1hfqn94gq7zj30u0140grh.jpg", "width": 960, "height": 1280, "cut_type": 1, "type": null}, "object_id": "1042018:ac91fb05f2bf73fa6e87054e55edb265", "pic_id": "008tAhYMly1hfqn94gq7zj30u0140grh", "photo_tag": 0, "type": "pic", "pic_status": 0}}, "is_paid": false, "mblog_vip_type": 0, "number_display_strategy": {"apply_scenario_flag": 3, "display_text_min_number": 1000000, "display_text": "100万+"}, "reposts_count": 0, "comments_count": 0, "attitudes_count": 0, "attitudes_status": 0, "isLongText": false, "mlevel": 128, "complaint": {"showcontent": "此内容为不实消息，已处理。", "color": 1, "url": "http://service.account.weibo.com/show?rid=K1CeK8w9c7KYi", "actionlog": {"act_code": 6528, "fid": null, "lfid": null, "uicode": null, "luicode": null, "ext": "uid:7766225324|mid:4921601806829078|mlevel:128"}}, "content_auth": 0, "is_show_bulletin": 2, "comment_manage_info": {"comment_permission_type": -1, "approval_comment_type": 0, "comment_sort_type": 0}, "share_repost_type": 0, "tag_struct": [{"tag_name": "胡桃里音乐酒馆(郑州上悦城购物中心店)", "tag_scheme": "sinaweibo://cardlist?containerid=2306570042B2094252D164A2F9479F", "url_type_pic": "https://h5.sinaimg.cn/upload/100/972/2022/06/13/timeline_location.png", "oid": "1022:100101B2094252D164A2F9479F", "otype": "place", "tag_type": 1, "tag_hidden": 2, "ori_url": "http://t.cn/A6f5TG0K", "actionlog": {"act_code": 2413, "oid": "1022:100101B2094252D164A2F9479F", "uicode": null, "luicode": null, "fid": null, "ext": "orifid:"}, "desc": "河南四川菜榜第11名", "is_checkin": 1}], "title": {"text": "公开", "base_color": 1, "icon_url": "http://h5.sinaimg.cn/upload/2015/07/14/34/timeline_title_public.png"}, "mblogtype": 0, "showFeedRepost": false, "showFeedComment": false, "pictureViewerSign": false, "showPictureViewer": false, "rcList": [], "text": "发财的机会来了，本年度最佳风口！一夜暴富的机会！  ​​​", "region_name": "发布于 河南", "customIcons": [], "ok": 1, "proof": "经查，此微博配图称“郑州男子悬赏千万寻狗”不实，郑州警方已发布警情通报：此信息系杜撰，已对违法行为人依法查处。 详情：https://weibo.com/1784473157/N9ouclUoi。被投诉人言论构成“发布不实信息”，现根据《微博投诉操作细则》（https://service.account.weibo.com/roles/xize）第八章，对被举报人处理如下：扣除信用历史分10分。上述处理在公布后60分钟内生效。"}