{"visible": {"type": 0, "list_id": 0}, "created_at": "Fri May 03 10:05:49 +0800 2024", "id": 5029886894801411, "idstr": "5029886894801411", "mid": "5029886894801411", "mblogid": "OcxuFk947", "user": {"id": 2028810631, "idstr": "2028810631", "pc_new": 7, "screen_name": "新浪新闻", "profile_image_url": "https://tvax4.sinaimg.cn/crop.0.0.799.799.50/002diGk7ly8h8vg36oqidj60m70m7mxs02.jpg?KID=imgbed,tva&amp;Expires=1714812699&amp;ssig=9nJJD7dO2R", "profile_url": "/u/2028810631", "verified": true, "verified_type": 3, "domain": "sinapapers", "weihao": "", "verified_type_ext": 0, "avatar_large": "https://tvax4.sinaimg.cn/crop.0.0.799.799.180/002diGk7ly8h8vg36oqidj60m70m7mxs02.jpg?KID=imgbed,tva&amp;Expires=1714812699&amp;ssig=dwNFgB3KCV", "avatar_hd": "https://tvax4.sinaimg.cn/crop.0.0.799.799.1024/002diGk7ly8h8vg36oqidj60m70m7mxs02.jpg?KID=imgbed,tva&amp;Expires=1714812699&amp;ssig=f5hVQitF0E", "follow_me": false, "following": false, "mbrank": 2, "mbtype": 12, "v_plus": 0, "planet_video": false, "icon_list": [{"type": "vip", "data": {"mbrank": 2, "mbtype": 12, "svip": 1, "vvip": 1}}, {"type": "icon", "data": {"value": "1", "icon_img": "https://h5.sinaimg.cn/upload/106/1683/2024/03/07/feed_icon_2024chuntian2x.png", "title": "你好春天", "url": "https://s.weibo.com/weibo?q=%23你好春天%23"}}]}, "can_edit": false, "text_raw": "#大马一男校长涉性侵3男生获保释#【大马版素媛案？[吃惊]男校长被控性侵三男生 交了两万多当庭获保释】据时间视频：当地时间4月30日，马来西亚吉兰丹马樟一30岁校长被控性侵3名学生，但在庭上拒不认罪。根据控状，被告涉嫌性侵3名12至15岁男学生。控方担心他骚扰证人不让其保释。辩方以当事人需要养家 ​​​", "textLength": 433, "source": "&lt;a target=\"_blank\" href=\"https://t.sina.com.cn\" rel=\"nofollow\"&gt;微博视频号&lt;/a&gt;", "favorited": false, "rid": "0_0_0_5226138926158881089_0_0_0", "cardid": "star_1723", "pic_ids": [], "pic_num": 0, "is_paid": false, "pic_bg_new": "http://vip.storage.weibo.com/feed_cover/star_1723_mobile_new.png?version=20240410", "mblog_vip_type": 0, "reposts_count": 2, "comments_count": 9, "attitudes_count": 32, "attitudes_status": 0, "continue_tag": {"title": "全文", "pic": "http://h5.sinaimg.cn/upload/2015/09/25/3/timeline_card_small_article.png", "scheme": "sinaweibo://detail?mblogid=5029886894801411&amp;id=5029886894801411&amp;next_fid=232532_mblog&amp;feed_detail_type=0"}, "isLongText": true, "mlevel": 0, "content_auth": 0, "is_show_bulletin": 2, "comment_manage_info": {"comment_permission_type": -1, "approval_comment_type": 0, "comment_sort_type": 0}, "share_repost_type": 0, "topic_struct": [{"title": "", "topic_url": "sinaweibo://searchall?containerid=231522&amp;q=%23%E5%A4%A7%E9%A9%AC%E4%B8%80%E7%94%B7%E6%A0%A1%E9%95%BF%E6%B6%89%E6%80%A7%E4%BE%B53%E7%94%B7%E7%94%9F%E8%8E%B7%E4%BF%9D%E9%87%8A%23&amp;extparam=%23%E5%A4%A7%E9%A9%AC%E4%B8%80%E7%94%B7%E6%A0%A1%E9%95%BF%E6%B6%89%E6%80%A7%E4%BE%B53%E7%94%B7%E7%94%9F%E8%8E%B7%E4%BF%9D%E9%87%8A%23", "topic_title": "大马一男校长涉性侵3男生获保释", "actionlog": {"act_type": 1, "act_code": 300, "oid": "1022:2315221f219cd78f25d088bc5d87e4bd2acde8", "uuid": 5029886895849517, "cardid": "", "lcardid": "", "uicode": "", "luicode": "", "fid": "", "lfid": "", "ext": "mid:5029886894801411|rid:0_0_0_5226138926158881089_0_0_0|short_url:|long_url:|comment_id:|miduid:2028810631|rootmid:5029886894801411|rootuid:2028810631|authorid:|uuid:5029886895849517|is_ad_weibo:0"}}], "url_struct": [{"url_title": "时间视频的微博视频", "url_type_pic": "https://h5.sinaimg.cn/upload/2015/09/25/3/timeline_card_small_video.png", "ori_url": "sinaweibo://video/vvs?mid=5029886894801411&amp;object_id=1034:5029883185922068&amp;url_type=39&amp;object_type=video&amp;pos=1", "page_id": "2304445029883185922068", "short_url": "http://t.cn/A6HPhbrW", "long_url": "https://video.weibo.com/show?fid=1034:5029883185922068", "url_type": 39, "result": false, "actionlog": {"act_type": 1, "act_code": 300, "oid": "1034:5029883185922068", "uuid": 5029883205124316, "cardid": "", "lcardid": "", "uicode": "", "luicode": "", "fid": "", "lfid": "", "ext": "mid:5029886894801411|rid:0_0_0_5226138926158881089_0_0_0|short_url:http://t.cn/A6HPhbrW|long_url:https://video.weibo.com/show?fid=1034:5029883185922068|comment_id:|miduid:2028810631|rootmid:5029886894801411|rootuid:2028810631|authorid:6250824982|uuid:5029883205124316|is_ad_weibo:0|analysis_card:url_struct"}, "storage_type": "oss", "hide": 0, "object_type": "", "ttl": 3600, "h5_target_url": "https://video.weibo.com/show?fid=1034:5029883185922068&amp;from=1FFFF96039&amp;weiboauthoruid=2028810631", "need_save_obj": 0}], "title": {"text": "公开", "base_color": 1, "icon_url": "http://h5.sinaimg.cn/upload/2015/07/14/34/timeline_title_public.png"}, "mblogtype": 0, "showFeedRepost": false, "showFeedComment": false, "pictureViewerSign": false, "showPictureViewer": false, "rcList": [], "text": "&lt;a href=\"//s.weibo.com/weibo?q=%23%E5%A4%A7%E9%A9%AC%E4%B8%80%E7%94%B7%E6%A0%A1%E9%95%BF%E6%B6%89%E6%80%A7%E4%BE%B53%E7%94%B7%E7%94%9F%E8%8E%B7%E4%BF%9D%E9%87%8A%23\" target=\"_blank\"&gt;#大马一男校长涉性侵3男生获保释#&lt;/a&gt;【大马版素媛案？&lt;img alt=\"[吃惊]\" title=\"[吃惊]\" src=\"https://face.t.sinajs.cn/t4/appstyle/expression/ext/normal/49/2018new_chijing_org.png\" /&gt;男校长被控性侵三男生 交了两万多当庭获保释】据时间视频：当地时间4月30日，马来西亚吉兰丹马樟一30岁校长被控性侵3名学生，但在庭上拒不认罪。根据控状，被告涉嫌性侵3名12至15岁男学生。控方担心他骚扰证人不让其保释。辩方以当事人需要养家 ​​​ ...&lt;span class=\"expand\"&gt;展开&lt;/span&gt;", "customIcons": [], "page_info": {"type": "11", "page_id": "2304445029883185922068", "object_type": "video", "object_id": "1034:5029883185922068", "content1": "时间视频的微博视频", "content2": "【大马版素媛案？[吃惊]男校长被控性侵三男生 交了两万多当庭获保释】#马来西亚一男校长被控性侵三男生# 当地时间4月30日，马来西亚吉兰丹马樟一30岁校长被控性侵3名学生，但在庭上拒不认罪。根据控状，被告涉嫌性侵3名12至15岁男学生。控方担心他骚扰证人不让其保释。辩方以当事人需", "act_status": 1, "media_info": {"name": "时间视频的微博视频", "stream_url": "http://f.video.weibocdn.com/o0/T0C32qPrlx08eyHxipq0010412005bri0E010.mp4?label=mp4_720p&amp;template=720x1268.24.0&amp;ori=0&amp;ps=1CwnkDw1GXwCQx&amp;Expires=1714805499&amp;ssig=uTNAynrhYE&amp;KID=unistore,video", "stream_url_hd": "http://f.video.weibocdn.com/o0/T0C32qPrlx08eyHxipq0010412005bri0E010.mp4?label=mp4_720p&amp;template=720x1268.24.0&amp;ori=0&amp;ps=1CwnkDw1GXwCQx&amp;Expires=1714805499&amp;ssig=uTNAynrhYE&amp;KID=unistore,video", "format": "mp4", "h5_url": "https://video.weibo.com/show?fid=1034:5029883185922068", "mp4_sd_url": "http://f.video.weibocdn.com/o0/T0C32qPrlx08eyHxipq0010412005bri0E010.mp4?label=mp4_720p&amp;template=720x1268.24.0&amp;ori=0&amp;ps=1CwnkDw1GXwCQx&amp;Expires=1714805499&amp;ssig=uTNAynrhYE&amp;KID=unistore,video", "mp4_hd_url": "http://f.video.weibocdn.com/o0/T0C32qPrlx08eyHxipq0010412005bri0E010.mp4?label=mp4_720p&amp;template=720x1268.24.0&amp;ori=0&amp;ps=1CwnkDw1GXwCQx&amp;Expires=1714805499&amp;ssig=uTNAynrhYE&amp;KID=unistore,video", "h265_mp4_hd": "http://f.video.weibocdn.com/o0/T0C32qPrlx08eyHxipq0010412005bri0E010.mp4?label=mp4_720p&amp;template=720x1268.24.0&amp;ori=0&amp;ps=1CwnkDw1GXwCQx&amp;Expires=1714805499&amp;ssig=uTNAynrhYE&amp;KID=unistore,video", "h265_mp4_ld": "http://f.video.weibocdn.com/o0/T0C32qPrlx08eyHxipq0010412005bri0E010.mp4?label=mp4_720p&amp;template=720x1268.24.0&amp;ori=0&amp;ps=1CwnkDw1GXwCQx&amp;Expires=1714805499&amp;ssig=uTNAynrhYE&amp;KID=unistore,video", "inch_4_mp4_hd": "http://f.video.weibocdn.com/o0/T0C32qPrlx08eyHxipq0010412005bri0E010.mp4?label=mp4_720p&amp;template=720x1268.24.0&amp;ori=0&amp;ps=1CwnkDw1GXwCQx&amp;Expires=1714805499&amp;ssig=uTNAynrhYE&amp;KID=unistore,video", "inch_5_mp4_hd": "http://f.video.weibocdn.com/o0/T0C32qPrlx08eyHxipq0010412005bri0E010.mp4?label=mp4_720p&amp;template=720x1268.24.0&amp;ori=0&amp;ps=1CwnkDw1GXwCQx&amp;Expires=1714805499&amp;ssig=uTNAynrhYE&amp;KID=unistore,video", "inch_5_5_mp4_hd": "http://f.video.weibocdn.com/o0/T0C32qPrlx08eyHxipq0010412005bri0E010.mp4?label=mp4_720p&amp;template=720x1268.24.0&amp;ori=0&amp;ps=1CwnkDw1GXwCQx&amp;Expires=1714805499&amp;ssig=uTNAynrhYE&amp;KID=unistore,video", "mp4_720p_mp4": "http://f.video.weibocdn.com/o0/T0C32qPrlx08eyHxipq0010412005bri0E010.mp4?label=mp4_720p&amp;template=720x1268.24.0&amp;ori=0&amp;ps=1CwnkDw1GXwCQx&amp;Expires=1714805499&amp;ssig=uTNAynrhYE&amp;KID=unistore,video", "hevc_mp4_720p": "", "prefetch_type": 1, "prefetch_size": 262144, "act_status": 1, "protocol": "general,dash", "media_id": "5029883185922068", "origin_total_bitrate": 6014838, "video_orientation": "vertical", "duration": 12, "forward_strategy": -1, "search_scheme": "sinaweibo://svssearch?containerid=232080", "is_short_video": 0, "vote_is_show": 0, "belong_collection": 0, "titles_display_time": "3", "show_progress_bar": 1, "show_mute_button": true, "ext_info": {"video_orientation": "vertical"}, "next_title": "#大马一男校长涉性侵3男生获保释#【大马版素媛案？[吃惊]男校长被控性侵三男生 交了两万多当庭获保释】据时间视频：当地时间4月30日，马来西亚吉兰丹马樟一30岁校长被控性侵3名学生，但在庭上拒不认罪。根据控状，被告涉嫌性侵3名12至15岁男学生。控方担心他骚扰证人不让其保释。辩方以当事人需要养家", "kol_title": "#大马一男校长涉性侵3男生获保释#【大马版素媛案？[吃惊]男校长被控性侵三男生 交了两万多当庭获保释】据时间视频：当地时间4月30日，马来西亚吉兰丹马樟一30岁校长被控性侵3名学生，但在庭上拒不认罪。根据控状，被告涉嫌性侵3名12至15岁男学生。控方担心他骚扰证人不让其保释。辩方以当事人需要养家", "play_completion_actions": [{"type": "1", "icon": "https://h5.sinaimg.cn/upload/100/1413/2021/12/22/feed_video_icon_replay.png", "text": "重播", "link": "", "btn_code": 1000, "show_position": 1, "actionlog": {"oid": "2304445029883185922068", "act_code": 1221, "act_type": 0, "source": "video"}}, {"type": 6, "icon": "https://tvax4.sinaimg.cn/crop.0.0.888.888.180/006P1P7Mly8h8vg7e1x1lj30oo0oo0ub.jpg?KID=imgbed,tva&amp;Expires=1714812699&amp;ssig=n3PeKvOsFz", "text": "", "display_mode": 2, "display_starttime": 5, "display_endtime": 99999, "countdown_time": 5, "show_position": 48, "scheme": "", "link": "", "btn_code": 1009, "actionlog": {"oid": "2304445029883185922068", "act_code": 91, "act_type": 0, "source": "video", "ext": "mid:5029886894801411|oid:1034:5029883185922068|muid:2028810631|authorid:6250824982"}, "ext": {"uid": "6250824982", "user_name": "时间视频", "followers_count": 10505787, "verified": true, "verified_type": 3, "verified_reason": "北京时间旗下泛资讯短视频平台", "level": 3}, "display_type": 0}], "video_publish_time": 1714701069, "play_loop_type": 0, "author_mid": "5029883829290085", "author_name": "时间视频", "extra_info": {"sceneid": "feed"}, "video_download_strategy": {"abandon_download": 0}, "jump_to": 6, "big_pic_info": {"pic_big": {"height": 1906, "url": "https://wx2.sinaimg.cn/orj1080/006P1P7Mly1hpc37t4g09j30u01gy4ak.jpg", "width": 1080}, "pic_small": {"height": 317, "url": "https://wx2.sinaimg.cn/or180/006P1P7Mly1hpc37t4g09j30u01gy4ak.jpg", "width": 180}, "pic_middle": {"height": 635, "url": "https://wx2.sinaimg.cn/or360/006P1P7Mly1hpc37t4g09j30u01gy4ak.jpg", "width": 360}}, "online_users": "16.3万次观看", "online_users_number": 163619, "ttl": 3600, "storage_type": "oss", "is_keep_current_mblog": 0, "has_recommend_video": 1, "author_info": {"id": 6250824982, "idstr": "6250824982", "pc_new": 7, "screen_name": "时间视频", "profile_image_url": "https://tvax4.sinaimg.cn/crop.0.0.888.888.50/006P1P7Mly8h8vg7e1x1lj30oo0oo0ub.jpg?KID=imgbed,tva&amp;Expires=1714812699&amp;ssig=h%2F5E50kV%2F0", "profile_url": "/u/6250824982", "verified": true, "verified_type": 3, "domain": "", "weihao": "", "verified_type_ext": 0, "avatar_large": "https://tvax4.sinaimg.cn/crop.0.0.888.888.180/006P1P7Mly8h8vg7e1x1lj30oo0oo0ub.jpg?KID=imgbed,tva&amp;Expires=1714812699&amp;ssig=n3PeKvOsFz", "avatar_hd": "https://tvax4.sinaimg.cn/crop.0.0.888.888.1024/006P1P7Mly8h8vg7e1x1lj30oo0oo0ub.jpg?KID=imgbed,tva&amp;Expires=1714812699&amp;ssig=5WytfSVOc4", "follow_me": false, "following": false, "mbrank": 2, "mbtype": 12, "v_plus": 0, "planet_video": false, "verified_reason": "北京时间旗下泛资讯短视频平台", "description": "有偿征集突发报料、视频投稿，投稿方式：北京时间网站/APP-个人主页-时间拍客；邮箱：shijianshipin@sina.com", "location": "北京", "gender": "m", "followers_count": 10505788, "followers_count_str": "1050.6万", "friends_count": 607, "statuses_count": 78337, "url": "", "svip": 1, "vvip": 1, "cover_image_phone": "https://wx1.sinaimg.cn/crop.0.0.640.640.640/006P1P7Mly1hgjn63o8obj30wr0wr443.jpg"}, "playback_list": [{"meta": {"label": "mp4_1080p", "quality_index": 1080, "quality_desc": "高清", "quality_label": "1080p", "quality_class": "HD", "type": 1, "quality_group": 1080, "is_hidden": false}, "play_info": {"type": 1, "mime": "video/mp4", "protocol": "general", "label": "mp4_1080p", "url": "https://f.video.weibocdn.com/o0/zAfyQyBtlx08eyHxIsgg010412008MR10E010.mp4?label=mp4_1080p&amp;template=1080x1906.24.0&amp;media_id=5029883185922068&amp;tp=8x8A3El:YTkl0eM8&amp;us=0&amp;ori=1&amp;bf=4&amp;ot=v&amp;lp=000045bKLX&amp;ps=mZ6WB&amp;uid=7sSuzF&amp;ab=,8012-g2,8013-g0,3601-g27&amp;Expires=1714805499&amp;ssig=74n4JAqNKc&amp;KID=unistore,video", "bitrate": 1356382, "prefetch_range": "0-693384", "video_codecs": "avc1.640032", "fps": 30, "width": 1080, "height": 1906, "size": 2094423, "duration": 12.352, "sar": "0.0", "audio_codecs": "mp4a.40.5", "audio_sample_rate": 44100, "quality_label": "1080p", "quality_class": "HD", "quality_desc": "高清", "audio_channels": 2, "audio_sample_fmt": "fltp", "audio_bits_per_sample": 0, "watermark": "none", "extension": {"transcode_info": {"pcdn_rule_id": 0, "pcdn_jank": 0, "origin_video_dr": "SDR", "ab_strategies": ",8012-g2,8013-g0,3601-g27"}}, "video_decoder": "hard", "prefetch_enabled": true, "tcp_receive_buffer": 262144, "dolby_atmos": false, "color_transfer": "bt709", "stereo_video": 0, "first_pkt_end_pos": 102881}}, {"meta": {"label": "mp4_720p", "quality_index": 720, "quality_desc": "高清", "quality_label": "720p", "quality_class": "HD", "type": 1, "quality_group": 720, "is_hidden": false}, "play_info": {"type": 1, "mime": "video/mp4", "protocol": "general", "label": "mp4_720p", "url": "https://f.video.weibocdn.com/o0/T0C32qPrlx08eyHxipq0010412005bri0E010.mp4?label=mp4_720p&amp;template=720x1268.24.0&amp;media_id=5029883185922068&amp;tp=8x8A3El:YTkl0eM8&amp;us=0&amp;ori=1&amp;bf=4&amp;ot=v&amp;lp=000045bKLX&amp;ps=mZ6WB&amp;uid=7sSuzF&amp;ab=,8012-g2,8013-g0,3601-g27&amp;Expires=1714805499&amp;ssig=uTNAynrhYE&amp;KID=unistore,video", "bitrate": 800205, "prefetch_range": "0-406038", "video_codecs": "avc1.64001f", "fps": 30, "width": 720, "height": 1268, "size": 1235616, "duration": 12.352, "sar": "0.0", "audio_codecs": "mp4a.40.5", "audio_sample_rate": 44100, "quality_label": "720p", "quality_class": "HD", "quality_desc": "高清", "audio_channels": 2, "audio_sample_fmt": "fltp", "audio_bits_per_sample": 0, "watermark": "none", "extension": {"transcode_info": {"pcdn_rule_id": 0, "pcdn_jank": 0, "origin_video_dr": "SDR", "ab_strategies": ",8012-g2,8013-g0,3601-g27"}}, "video_decoder": "hard", "prefetch_enabled": true, "tcp_receive_buffer": 262144, "dolby_atmos": false, "color_transfer": "bt709", "stereo_video": 0, "first_pkt_end_pos": 40693}}, {"meta": {"label": "mp4_hd", "quality_index": 480, "quality_desc": "标清", "quality_label": "480p", "quality_class": "SD", "type": 1, "quality_group": 480, "is_hidden": false}, "play_info": {"type": 1, "mime": "video/mp4", "protocol": "general", "label": "mp4_hd", "url": "https://f.video.weibocdn.com/o0/k5KuHa4Blx08eyHxecli010412003irt0E010.mp4?label=mp4_hd&amp;template=540x952.24.0&amp;media_id=5029883185922068&amp;tp=8x8A3El:YTkl0eM8&amp;us=0&amp;ori=1&amp;bf=4&amp;ot=v&amp;lp=000045bKLX&amp;ps=mZ6WB&amp;uid=7sSuzF&amp;ab=,8012-g2,8013-g0,3601-g27&amp;Expires=1714805499&amp;ssig=KOdGRYdHJi&amp;KID=unistore,video", "bitrate": 508948, "prefetch_range": "0-262761", "video_codecs": "avc1.64001f", "fps": 30, "width": 540, "height": 952, "size": 785879, "duration": 12.352, "sar": "0.0", "audio_codecs": "mp4a.40.5", "audio_sample_rate": 44100, "quality_label": "480p", "quality_class": "SD", "quality_desc": "标清", "audio_channels": 2, "audio_sample_fmt": "fltp", "audio_bits_per_sample": 0, "watermark": "none", "extension": {"transcode_info": {"pcdn_rule_id": 0, "pcdn_jank": 0, "origin_video_dr": "SDR", "ab_strategies": ",8012-g2,8013-g0,3601-g27"}}, "video_decoder": "hard", "prefetch_enabled": true, "tcp_receive_buffer": 262144, "dolby_atmos": false, "color_transfer": "bt709", "stereo_video": 0, "first_pkt_end_pos": 31817}}, {"meta": {"label": "scrubber_hd", "quality_index": 480, "quality_desc": "标清", "quality_label": "480p", "quality_class": "SD", "type": 3, "quality_group": 480, "is_hidden": false}, "play_info": {"type": 3, "mime": "image/jpeg", "protocol": "general", "label": "scrubber_hd", "url": "https://wx2.sinaimg.cn/large/006P1P7Mly1hpc3a23a6fj30f07eowi9.jpg?media_id=5029883185922068&amp;tp=8x8A3El:YTkl0eM8&amp;us=0&amp;ori=1&amp;bf=4&amp;ot=v&amp;lp=000045bKLX&amp;ps=mZ6WB&amp;uid=7sSuzF&amp;ab=,8012-g2,8013-g0,3601-g27&amp;Expires=1714805499&amp;ssig=8J9rS6VIoz&amp;KID=unistore,video", "prefetch_range": "0-512000", "width": 180, "height": 320, "quality_label": "480p", "quality_class": "SD", "quality_desc": "标清", "extension": {"transcode_info": {"pcdn_rule_id": 0, "pcdn_jank": 0, "origin_video_dr": "SDR", "ab_strategies": ",8012-g2,8013-g0,3601-g27"}}, "video_decoder": "hard", "prefetch_enabled": true, "tcp_receive_buffer": 262144, "col": 3, "row": 30, "interval": 1, "offset": 0.5, "urls": ["http://wx4.sinaimg.cn/large/006P1P7Mly1hpc3a23a6fj30f07eowi9.jpg"]}}, {"meta": {"label": "mp4_ld", "quality_index": 360, "quality_desc": "流畅", "quality_label": "360p", "quality_class": "SD", "type": 1, "quality_group": 360, "is_hidden": false}, "play_info": {"type": 1, "mime": "video/mp4", "protocol": "general", "label": "mp4_ld", "url": "https://f.video.weibocdn.com/o0/DGOruD6mlx08eyHwXUDC010412001RBF0E010.mp4?label=mp4_ld&amp;template=360x632.24.0&amp;media_id=5029883185922068&amp;tp=8x8A3El:YTkl0eM8&amp;us=0&amp;ori=1&amp;bf=4&amp;ot=v&amp;lp=000045bKLX&amp;ps=mZ6WB&amp;uid=7sSuzF&amp;ab=,8012-g2,8013-g0,3601-g27&amp;Expires=1714805499&amp;ssig=wxR4DQ%2FcGy&amp;KID=unistore,video", "bitrate": 287797, "prefetch_range": "0-152396", "video_codecs": "avc1.64001e", "fps": 30, "width": 360, "height": 632, "size": 444395, "duration": 12.352, "sar": "0.0", "audio_codecs": "mp4a.40.5", "audio_sample_rate": 44100, "quality_label": "360p", "quality_class": "SD", "quality_desc": "流畅", "audio_channels": 2, "audio_sample_fmt": "fltp", "audio_bits_per_sample": 0, "watermark": "none", "extension": {"transcode_info": {"pcdn_rule_id": 0, "pcdn_jank": 0, "origin_video_dr": "SDR", "ab_strategies": ",8012-g2,8013-g0,3601-g27"}}, "video_decoder": "hard", "prefetch_enabled": true, "tcp_receive_buffer": 262144, "dolby_atmos": false, "color_transfer": "bt709", "stereo_video": 0, "first_pkt_end_pos": 34641}}]}, "page_pic": "https://wx2.sinaimg.cn/orj480/006P1P7Mly1hpc37t4g09j30u01gy4ak.jpg", "page_title": "时间视频的微博视频", "page_url": "sinaweibo://infopage?containerid=2304445029883185922068&amp;containerid=2304445029883185922068&amp;url_type=39&amp;object_type=video&amp;pos=2", "pic_info": {"pic_big": {"height": "952", "url": "https://wx2.sinaimg.cn/orj480/006P1P7Mly1hpc37t4g09j30u01gy4ak.jpg", "width": "540"}, "pic_small": {"height": "952", "url": "https://wx2.sinaimg.cn/orj480/006P1P7Mly1hpc37t4g09j30u01gy4ak.jpg", "width": "540"}, "pic_middle": {"url": "https://wx2.sinaimg.cn/orj480/006P1P7Mly1hpc37t4g09j30u01gy4ak.jpg", "height": "952", "width": "540"}}, "oid": "6250824982", "type_icon": "", "author_id": "6250824982", "authorid": "6250824982", "warn": "", "actionlog": {"act_type": 1, "act_code": 799, "lcardid": "", "fid": "", "mid": "5029886894801411", "oid": "1034:5029883185922068", "uuid": 5029883205124316, "source": "video", "ext": "uid:6839654475|mid:5029886894801411|objectid:1034%3A5029883185922068|from:1|object_duration:12.352|miduid:2028810631|rootuid:2028810631|rootmid:5029886894801411|authorid:6250824982|video_orientation:vertical|third_vid:|is_album:0|is_contribution:0|video_tags:|isfan:0|ua:Mozilla/5.0 (Windows NT 10.0%3B Win64%3B x64) AppleWebKit/537.36 (KHTML, like Gecko) Chrome/123.0.0.0 Safari/537.36 WeiboPro/1.0.0|sceneid:feed|uuid:5029883205124316|detail:native|contribution:0|short_video:0|st_video:1|author_mid:5029883829290085|cluster_type_status:|is_ad_weibo:0|analysis_card:page_info"}, "short_url": "http://t.cn/A6HPhbrW"}, "ok": 1}