{"visible": {"type": 0, "list_id": 0}, "created_at": "Thu Oct 31 22:16:22 +0800 2019", "id": 4433580316987735, "idstr": "4433580316987735", "mid": "4433580316987735", "mblogid": "Ie5zNtjPp", "user": {"id": 3297396641, "idstr": "3297396641", "pc_new": 0, "screen_name": "紫枫愿望", "profile_image_url": "https://tva3.sinaimg.cn/crop.0.0.750.750.50/c48a47a1jw8f04zyl1z7yj20ku0ku78g.jpg?KID=imgbed,tva&amp;Expires=1713170061&amp;ssig=woabBtjbot", "profile_url": "/u/3297396641", "verified": false, "verified_type": -1, "domain": "", "weihao": "", "avatar_large": "https://tva3.sinaimg.cn/crop.0.0.750.750.180/c48a47a1jw8f04zyl1z7yj20ku0ku78g.jpg?KID=imgbed,tva&amp;Expires=1713170061&amp;ssig=3zQYMG%2BlXx", "avatar_hd": "https://tva3.sinaimg.cn/crop.0.0.750.750.1024/c48a47a1jw8f04zyl1z7yj20ku0ku78g.jpg?KID=imgbed,tva&amp;Expires=1713170061&amp;ssig=zZudIBmiA%2B", "follow_me": false, "following": false, "mbrank": 0, "mbtype": 0, "v_plus": 0, "planet_video": true, "icon_list": []}, "can_edit": false, "text_raw": "突发：无锡金桥附近加油站爆炸，伤者已送无锡第三人民医院！又是无锡[允悲]  http://t.cn/Ai1eaO5f ​​​", "textLength": 111, "annotations": [{"place": {"poiid": "B2094753D26EA3FF439B", "title": "玉成家园", "type": "checkin"}, "client_mblogid": "9d80c83b-0dfe-4124-986f-4a50d94ef770"}, {"mapi_request": true}], "source": "&lt;a target=\"_blank\" href=\"https://app.weibo.com/t/feed/5ui34Y\" rel=\"nofollow\"&gt;柔光自拍vivo X7&lt;/a&gt;", "favorited": false, "rid": "0_0_0_162554161307649636_0_0_0", "pic_ids": [], "geo": {"type": "Point", "coordinates": [31.384487, 120.60678], "detail": {"poiid": "B2094753D26EA3FF439B", "title": "玉成家园", "type": "checkin"}}, "pic_num": 0, "is_paid": false, "mblog_vip_type": 0, "number_display_strategy": {"apply_scenario_flag": 3, "display_text_min_number": 1000000, "display_text": "100万+"}, "reposts_count": 0, "comments_count": 4, "attitudes_count": 5, "attitudes_status": 0, "isLongText": false, "mlevel": 128, "complaint": {"showcontent": "此内容为不实消息，已处理。", "color": 1, "url": "http://service.account.weibo.com/show?rid=K1CaS6QBl6awm", "actionlog": {"act_code": 6528, "fid": null, "lfid": null, "uicode": null, "luicode": null, "ext": "uid:3297396641|mid:4433580316987735|mlevel:128"}}, "content_auth": 0, "is_show_bulletin": 2, "comment_manage_info": {"comment_permission_type": -1, "approval_comment_type": 0, "comment_sort_type": 0}, "share_repost_type": 0, "url_struct": [{"url_title": "紫枫愿望的微博视频", "url_type_pic": "https://h5.sinaimg.cn/upload/2015/09/25/3/timeline_card_small_video.png", "ori_url": "sinaweibo://video/vvs?mid=4433580316987735&amp;object_id=1034:4433580282290194&amp;url_type=39&amp;object_type=video&amp;pos=1", "page_id": "2304444433580282290194", "short_url": "http://t.cn/Ai1eaO5f", "long_url": "https://video.weibo.com/show?fid=1034:4433580282290194", "url_type": 39, "result": false, "actionlog": {"act_type": 1, "act_code": 300, "oid": "1034:4433580282290194", "uuid": 4433580288639514, "cardid": "", "lcardid": "", "uicode": "", "luicode": "", "fid": "", "lfid": "", "ext": "mid:4433580316987735|rid:0_0_0_162554161307649636_0_0_0|short_url:http://t.cn/Ai1eaO5f|long_url:https://video.weibo.com/show?fid=1034:4433580282290194|comment_id:|miduid:3297396641|rootmid:4433580316987735|rootuid:3297396641|authorid:3297396641|uuid:4433580288639514|is_ad_weibo:0|analysis_card:url_struct"}, "storage_type": "oss", "hide": 0, "object_type": "", "ttl": 3600, "h5_target_url": "https://video.weibo.com/show?fid=1034:4433580282290194&amp;from=1FFFF96039&amp;weiboauthoruid=3297396641", "need_save_obj": 0}], "tag_struct": [{"tag_name": "玉成家园", "tag_scheme": "sinaweibo://cardlist?containerid=2306570042B2094753D26EA3FF439B", "url_type_pic": "https://h5.sinaimg.cn/upload/100/972/2022/06/13/timeline_location.png", "oid": "1022:100101B2094753D26EA3FF439B", "otype": "place", "tag_type": 1, "tag_hidden": 2, "ori_url": "http://t.cn/z8yllsy", "actionlog": {"act_code": 2413, "oid": "1022:100101B2094753D26EA3FF439B", "uicode": null, "luicode": null, "fid": null, "ext": "orifid:"}, "desc": "苏州", "is_checkin": 1}], "title": {"text": "公开", "base_color": 1, "icon_url": "http://h5.sinaimg.cn/upload/2015/07/14/34/timeline_title_public.png"}, "mblogtype": 0, "showFeedRepost": false, "showFeedComment": false, "pictureViewerSign": false, "showPictureViewer": false, "rcList": [], "text": "突发：无锡金桥附近加油站爆炸，伤者已送无锡第三人民医院！又是无锡&lt;img alt=\"[允悲]\" title=\"[允悲]\" src=\"https://face.t.sinajs.cn/t4/appstyle/expression/ext/normal/83/2018new_kuxiao_org.png\" /&gt;  &lt;a target=\"_blank\" href=\"https://video.weibo.com/show?fid=1034:4433580282290194\"&gt;&lt;img class=\"icon-link\" src=\"https://h5.sinaimg.cn/upload/2015/09/25/3/timeline_card_small_video_default.png\"/&gt;紫枫愿望的微博视频&lt;/a&gt; ​​​", "customIcons": [], "page_info": {"type": "11", "page_id": "2304444433580282290194", "object_type": "video", "object_id": "1034:4433580282290194", "content1": "紫枫愿望的微博视频", "content2": "突发：无锡金桥附近加油站爆炸，伤者已送无锡第三人民医院！又是无锡[允悲] http://t.cn/z8yllsy", "act_status": 1, "media_info": {"name": "紫枫愿望的微博视频", "stream_url": "http://f.video.weibocdn.com/002vGiOylx07ye8xI9yU0104120012cX0E010.mp4?label=mp4_ld&amp;template=360x768.24.0&amp;trans_finger=81b11b8c5ffb62d33ceb3244bdd17e7b&amp;ori=0&amp;ps=1CwnkDw1GXwCQx&amp;Expires=1713162861&amp;ssig=iA5%2FUnHPfo&amp;KID=unistore,video", "stream_url_hd": "http://f.video.weibocdn.com/002jKPgslx07ye8xOLkA010412001BNt0E010.mp4?label=mp4_hd&amp;template=448x960.24.0&amp;trans_finger=6038099a530779e853bb78b617dbd3ab&amp;ori=0&amp;ps=1CwnkDw1GXwCQx&amp;Expires=1713162861&amp;ssig=%2FY4WStiVBS&amp;KID=unistore,video", "format": "mp4", "h5_url": "https://video.weibo.com/show?fid=1034:4433580282290194", "mp4_sd_url": "http://f.video.weibocdn.com/002vGiOylx07ye8xI9yU0104120012cX0E010.mp4?label=mp4_ld&amp;template=360x768.24.0&amp;trans_finger=81b11b8c5ffb62d33ceb3244bdd17e7b&amp;ori=0&amp;ps=1CwnkDw1GXwCQx&amp;Expires=1713162861&amp;ssig=iA5%2FUnHPfo&amp;KID=unistore,video", "mp4_hd_url": "http://f.video.weibocdn.com/002jKPgslx07ye8xOLkA010412001BNt0E010.mp4?label=mp4_hd&amp;template=448x960.24.0&amp;trans_finger=6038099a530779e853bb78b617dbd3ab&amp;ori=0&amp;ps=1CwnkDw1GXwCQx&amp;Expires=1713162861&amp;ssig=%2FY4WStiVBS&amp;KID=unistore,video", "h265_mp4_hd": "", "h265_mp4_ld": "", "inch_4_mp4_hd": "", "inch_5_mp4_hd": "", "inch_5_5_mp4_hd": "", "mp4_720p_mp4": "", "hevc_mp4_720p": "", "prefetch_type": 1, "prefetch_size": 262144, "act_status": 1, "protocol": "general", "media_id": "4433580282290194", "origin_total_bitrate": 0, "video_orientation": "vertical", "duration": 15, "forward_strategy": -1, "search_scheme": "sinaweibo://svssearch?containerid=232080", "is_short_video": 0, "vote_is_show": 0, "belong_collection": 0, "titles_display_time": "3", "show_progress_bar": 1, "show_mute_button": true, "ext_info": {"video_orientation": "vertical"}, "next_title": "突发：无锡金桥附近加油站爆炸，伤者已送无锡第三人民医院！又是无锡[允悲] http://t.cn/z8yllsy", "kol_title": "突发：无锡金桥附近加油站爆炸，伤者已送无锡第三人民医院！又是无锡[允悲] http://t.cn/z8yllsy", "play_completion_actions": [{"type": "1", "icon": "https://h5.sinaimg.cn/upload/100/1413/2021/12/22/feed_video_icon_replay.png", "text": "重播", "link": "", "btn_code": 1000, "show_position": 1, "actionlog": {"oid": "2304444433580282290194", "act_code": 1221, "act_type": 0, "source": "video"}}, {"type": 6, "icon": "https://tva3.sinaimg.cn/crop.0.0.750.750.180/c48a47a1jw8f04zyl1z7yj20ku0ku78g.jpg?KID=imgbed,tva&amp;Expires=1713170061&amp;ssig=3zQYMG%2BlXx", "text": "", "display_mode": 2, "display_starttime": 5, "display_endtime": 99999, "countdown_time": 5, "show_position": 48, "scheme": "", "link": "", "btn_code": 1009, "actionlog": {"oid": "2304444433580282290194", "act_code": 91, "act_type": 0, "source": "video", "ext": "mid:4433580316987735|oid:1034:4433580282290194|muid:3297396641|authorid:3297396641"}, "ext": {"uid": "3297396641", "user_name": "紫枫愿望", "followers_count": 49, "verified_type": -1, "level": 3}, "display_type": 0}], "video_publish_time": 1572531375, "play_loop_type": 0, "author_mid": "4433580316987735", "author_name": "紫枫愿望", "extra_info": {"sceneid": "feed"}, "video_download_strategy": {"abandon_download": 0}, "jump_to": 6, "online_users": "3980次观看", "online_users_number": 3980, "ttl": 3600, "storage_type": "oss", "is_keep_current_mblog": 0, "has_recommend_video": 1, "author_info": {"id": 3297396641, "idstr": "3297396641", "pc_new": 0, "screen_name": "紫枫愿望", "profile_image_url": "https://tva3.sinaimg.cn/crop.0.0.750.750.50/c48a47a1jw8f04zyl1z7yj20ku0ku78g.jpg?KID=imgbed,tva&amp;Expires=1713170061&amp;ssig=woabBtjbot", "profile_url": "/u/3297396641", "verified": false, "verified_type": -1, "domain": "", "weihao": "", "avatar_large": "https://tva3.sinaimg.cn/crop.0.0.750.750.180/c48a47a1jw8f04zyl1z7yj20ku0ku78g.jpg?KID=imgbed,tva&amp;Expires=1713170061&amp;ssig=3zQYMG%2BlXx", "avatar_hd": "https://tva3.sinaimg.cn/crop.0.0.750.750.1024/c48a47a1jw8f04zyl1z7yj20ku0ku78g.jpg?KID=imgbed,tva&amp;Expires=1713170061&amp;ssig=zZudIBmiA%2B", "follow_me": false, "following": false, "mbrank": 0, "mbtype": 0, "v_plus": 0, "planet_video": true, "description": "努力努力再努力", "location": "江苏", "gender": "f", "followers_count": 50, "followers_count_str": "50", "friends_count": 476, "statuses_count": 184, "url": "", "svip": 0, "vvip": 0, "cover_image_phone": "https://ww1.sinaimg.cn/crop.0.0.640.640.640/549d0121tw1egm1kjly3jj20hs0hsq4f.jpg"}, "playback_list": [{"meta": {"label": "mp4_hd", "quality_index": 480, "quality_desc": "标清", "quality_label": "480p", "quality_class": "SD", "type": 1, "quality_group": 480, "is_hidden": false}, "play_info": {"type": 1, "mime": "video/mp4", "protocol": "general", "label": "mp4_hd", "url": "https://f.video.weibocdn.com/002jKPgslx07ye8xOLkA010412001BNt0E010.mp4?label=mp4_hd&amp;template=448x960.24.0&amp;trans_finger=6038099a530779e853bb78b617dbd3ab&amp;media_id=4433580282290194&amp;tp=8x8A3El:YTkl0eM8&amp;us=0&amp;ori=1&amp;bf=4&amp;ot=v&amp;lp=000045bKNr&amp;ps=mZ6WB&amp;uid=8uaJsH&amp;ab=&amp;Expires=1713162861&amp;ssig=%2FY4WStiVBS&amp;KID=unistore,video", "bitrate": 202106, "prefetch_range": "0-91922", "video_codecs": "avc1.64001f", "fps": 17, "width": 448, "height": 960, "size": 383623, "duration": 15.185, "sar": "0.0", "audio_codecs": "mp4a.40.5", "audio_sample_rate": 44100, "quality_label": "480p", "quality_class": "SD", "quality_desc": "标清", "audio_channels": 2, "audio_sample_fmt": "fltp", "audio_bits_per_sample": 0, "watermark": "none", "extension": {"transcode_info": {"pcdn_rule_id": 0, "pcdn_jank": 0, "origin_video_dr": "SDR", "ab_strategies": ""}}, "video_decoder": "hard", "prefetch_enabled": true, "tcp_receive_buffer": 262144}}, {"meta": {"label": "mp4_ld", "quality_index": 360, "quality_desc": "流畅", "quality_label": "360p", "quality_class": "SD", "type": 1, "quality_group": 360, "is_hidden": false}, "play_info": {"type": 1, "mime": "video/mp4", "protocol": "general", "label": "mp4_ld", "url": "https://f.video.weibocdn.com/002vGiOylx07ye8xI9yU0104120012cX0E010.mp4?label=mp4_ld&amp;template=360x768.24.0&amp;trans_finger=81b11b8c5ffb62d33ceb3244bdd17e7b&amp;media_id=4433580282290194&amp;tp=8x8A3El:YTkl0eM8&amp;us=0&amp;ori=1&amp;bf=4&amp;ot=v&amp;lp=000045bKNr&amp;ps=mZ6WB&amp;uid=8uaJsH&amp;ab=&amp;Expires=1713162861&amp;ssig=iA5%2FUnHPfo&amp;KID=unistore,video", "bitrate": 130033, "prefetch_range": "0-62264", "video_codecs": "avc1.640016", "fps": 17, "width": 360, "height": 768, "size": 246819, "duration": 15.185, "sar": "0.0", "audio_codecs": "mp4a.40.5", "audio_sample_rate": 44100, "quality_label": "360p", "quality_class": "SD", "quality_desc": "流畅", "audio_channels": 2, "audio_sample_fmt": "fltp", "audio_bits_per_sample": 0, "watermark": "none", "extension": {"transcode_info": {"pcdn_rule_id": 0, "pcdn_jank": 0, "origin_video_dr": "SDR", "ab_strategies": ""}}, "video_decoder": "hard", "prefetch_enabled": true, "tcp_receive_buffer": 262144}}]}, "page_pic": "https://wx2.sinaimg.cn/orj480/c48a47a1gy1g8hqrw5rchj20cg0qogma.jpg", "page_title": "紫枫愿望的微博视频", "page_url": "sinaweibo://infopage?containerid=2304444433580282290194&amp;containerid=2304444433580282290194&amp;url_type=39&amp;object_type=video&amp;pos=2", "pic_info": {"pic_big": {"height": "960", "url": "https://wx2.sinaimg.cn/orj480/c48a47a1gy1g8hqrw5rchj20cg0qogma.jpg", "width": "448"}, "pic_small": {"height": "960", "url": "https://wx2.sinaimg.cn/orj480/c48a47a1gy1g8hqrw5rchj20cg0qogma.jpg", "width": "448"}, "pic_middle": {"url": "https://wx2.sinaimg.cn/orj480/c48a47a1gy1g8hqrw5rchj20cg0qogma.jpg", "height": "960", "width": "448"}}, "oid": "3297396641", "type_icon": "", "author_id": "3297396641", "authorid": "3297396641", "warn": "", "actionlog": {"act_type": 1, "act_code": 799, "lcardid": "", "fid": "", "mid": "4433580316987735", "oid": "1034:4433580282290194", "uuid": 4433580288639514, "source": "video", "ext": "uid:7774910775|mid:4433580316987735|objectid:1034%3A4433580282290194|from:1|object_duration:15.185|miduid:3297396641|rootuid:3297396641|rootmid:4433580316987735|authorid:3297396641|video_orientation:vertical|third_vid:|is_album:0|is_contribution:0|video_tags:|isfan:0|ua:Mozilla/5.0 (Windows NT 10.0%3B Win64%3B x64) AppleWebKit/537.36 (KHTML, like Gecko) Chrome/123.0.0.0 Safari/537.36 WeiboPro/1.0.0|sceneid:feed|uuid:4433580288639514|detail:native|contribution:0|short_video:0|st_video:1|author_mid:4433580316987735|cluster_type_status:|is_ad_weibo:0|analysis_card:page_info"}, "short_url": "http://t.cn/Ai1eaO5f"}, "ok": 1, "proof": "经查，该微博发视频称 “无锡加油站爆炸了”不实，@无锡消防 已发布火情通报：经初步勘察，现场为废弃油桶发生爆炸，主要燃烧物质为垃圾和草坪，过火面积约50平方米，明火已被扑灭。详情：https://weibo.com/2258778610/Ie4D9qAtW，被举报人言论属于构成“发布不实信息”，现根据《微博举报投诉操作细则》（http://service.account.weibo.com/roles/guiding）第19条，对被举报人处理如下：扣除信用积分2分。上述处理在公布后60分钟内生效。"}