{"visible": {"type": 0, "list_id": 0}, "created_at": "Wed May 13 15:44:55 +0800 2020", "id": 4504147443161584, "idstr": "4504147443161584", "mid": "4504147443161584", "mblogid": "J1JTqdgti", "user": {"id": 5738729933, "idstr": "5738729933", "pc_new": 7, "screen_name": "导演曾伏虎", "profile_image_url": "https://tva2.sinaimg.cn/crop.15.320.1000.1000.50/006gn7Odjw8eyq82jysgpj30xc1e0wo0.jpg?KID=imgbed,tva&amp;Expires=1713770482&amp;ssig=d2BRzcXDe4", "profile_url": "/u/5738729933", "verified": false, "verified_type": -1, "domain": "zengfuhu", "weihao": "", "avatar_large": "https://tva2.sinaimg.cn/crop.15.320.1000.1000.180/006gn7Odjw8eyq82jysgpj30xc1e0wo0.jpg?KID=imgbed,tva&amp;Expires=1713770482&amp;ssig=Rl%2BRhAMmzW", "avatar_hd": "https://tva2.sinaimg.cn/crop.15.320.1000.1000.1024/006gn7Odjw8eyq82jysgpj30xc1e0wo0.jpg?KID=imgbed,tva&amp;Expires=1713770482&amp;ssig=sYkJJJOQJV", "follow_me": false, "following": false, "mbrank": 3, "mbtype": 2, "v_plus": 0, "planet_video": false, "icon_list": []}, "can_edit": false, "text_raw": "绍兴城管5月11日上午十点左右，公然围攻抢有主人带有牵绳的狗，在温馨花园城管在抢一个工人的狗，狗的主人是农民工，狗没有伤人，还牵着狗绳，请大家发声，主人拼尽全力保护自己的爱犬，却被城管部门拼命抢夺其手上的狗！狗是主人的私有财产，城管野蛮执法严重违反巜物权法》。\n\n#导演曾伏虎# ​​​", "textLength": 337, "annotations": [{"client_mblogid": "iPhone-A87D1F1D-BFBD-49E6-896D-6EC0E134D6C9"}, {"mapi_request": true}], "source": "iPhone客户端", "favorited": false, "rid": "0_0_0_162787764577892897_0_0_0", "pic_ids": ["006gn7Odly1geqv93jreij30u019mqcv"], "pic_num": 1, "pic_infos": {"006gn7Odly1geqv93jreij30u019mqcv": {"thumbnail": {"url": "https://wx1.sinaimg.cn/wap180/006gn7Odly1geqv93jreij30u019mqcv.jpg", "width": 118, "height": 180, "cut_type": 1, "type": null}, "bmiddle": {"url": "https://wx1.sinaimg.cn/wap360/006gn7Odly1geqv93jreij30u019mqcv.jpg", "width": 236, "height": 360, "cut_type": 1, "type": null}, "large": {"url": "https://wx1.sinaimg.cn/orj960/006gn7Odly1geqv93jreij30u019mqcv.jpg", "width": 960, "height": 1459, "cut_type": 1, "type": null}, "original": {"url": "https://wx1.sinaimg.cn/orj1080/006gn7Odly1geqv93jreij30u019mqcv.jpg", "width": 1080, "height": 1642, "cut_type": 1, "type": null}, "largest": {"url": "https://wx1.sinaimg.cn/large/006gn7Odly1geqv93jreij30u019mqcv.jpg", "width": 1080, "height": 1642, "cut_type": 1, "type": null}, "mw2000": {"url": "https://wx1.sinaimg.cn/mw2000/006gn7Odly1geqv93jreij30u019mqcv.jpg", "width": 1080, "height": 1642, "cut_type": 1, "type": null}, "largecover": {"url": "https://wx1.sinaimg.cn/cmw960/006gn7Odly1geqv93jreij30u019mqcv.jpg", "width": 960, "height": 1459, "cut_type": 1, "type": null}, "object_id": "1042018:409cb3d63ff32fdcf91327fdcbb36c7d", "pic_id": "006gn7Odly1geqv93jreij30u019mqcv", "photo_tag": 0, "type": "pic", "pic_status": 0}}, "is_paid": false, "mblog_vip_type": 0, "number_display_strategy": {"apply_scenario_flag": 3, "display_text_min_number": 1000000, "display_text": "100万+"}, "reposts_count": 19, "comments_count": 10, "attitudes_count": 22, "attitudes_status": 0, "continue_tag": {"title": "全文", "pic": "http://h5.sinaimg.cn/upload/2015/09/25/3/timeline_card_small_article.png", "scheme": "sinaweibo://detail?mblogid=4504147443161584&amp;id=4504147443161584&amp;next_fid=232532_mblog&amp;feed_detail_type=0"}, "isLongText": true, "mlevel": 128, "complaint": {"showcontent": "此内容为不实消息，已处理。", "color": 1, "url": "http://service.account.weibo.com/show?rid=K1CeJ6w9l8q4f", "actionlog": {"act_code": 6528, "fid": null, "lfid": null, "uicode": null, "luicode": null, "ext": "uid:5738729933|mid:4504147443161584|mlevel:128"}}, "content_auth": 0, "is_show_bulletin": 2, "comment_manage_info": {"comment_permission_type": -1, "approval_comment_type": 0, "comment_sort_type": 0}, "share_repost_type": 0, "topic_struct": [{"title": "", "topic_url": "sinaweibo://searchall?containerid=231522&amp;q=%23%E5%AF%BC%E6%BC%94%E6%9B%BE%E4%BC%8F%E8%99%8E%23&amp;extparam=%23%E5%AF%BC%E6%BC%94%E6%9B%BE%E4%BC%8F%E8%99%8E%23", "topic_title": "导演曾伏虎", "actionlog": {"act_type": 1, "act_code": 300, "oid": "1022:2315225b3c923f9c084cc1d1b6c00f0aee0da6", "uuid": 4487090334073327, "cardid": "", "lcardid": "", "uicode": "", "luicode": "", "fid": "", "lfid": "", "ext": "mid:4504147443161584|rid:0_0_0_162787764577892897_0_0_0|short_url:|long_url:|comment_id:|miduid:5738729933|rootmid:4504147443161584|rootuid:5738729933|authorid:|uuid:4487090334073327|is_ad_weibo:0"}}, {"title": "", "topic_url": "sinaweibo://searchall?containerid=231522&amp;q=%23%E4%B8%AD%E5%8D%8E%E7%94%B0%E5%9B%AD%E7%8A%AC%23&amp;isnewpage=1", "topic_title": "中华田园犬", "actionlog": {"act_type": 1, "act_code": 300, "oid": "1022:2315226afa01a8618d63dc75e353bbbffb9f77", "uuid": 4213490662300782, "cardid": "", "lcardid": "", "uicode": "", "luicode": "", "fid": "", "lfid": "", "ext": "mid:4504147443161584|rid:0_0_0_162787764577892897_0_0_0|short_url:|long_url:|comment_id:|miduid:5738729933|rootmid:4504147443161584|rootuid:5738729933|authorid:|uuid:4213490662300782|is_ad_weibo:0"}}], "title": {"text": "公开", "base_color": 1, "icon_url": "http://h5.sinaimg.cn/upload/2015/07/14/34/timeline_title_public.png"}, "mblogtype": 0, "showFeedRepost": false, "showFeedComment": false, "pictureViewerSign": false, "showPictureViewer": false, "rcList": [], "text": "绍兴城管5月11日上午十点左右，公然围攻抢有主人带有牵绳的狗，在温馨花园城管在抢一个工人的狗，狗的主人是农民工，狗没有伤人，还牵着狗绳，请大家发声，主人拼尽全力保护自己的爱犬，却被城管部门拼命抢夺其手上的狗！狗是主人的私有财产，城管野蛮执法严重违反巜物权法》。&lt;br /&gt;&lt;br /&gt;&lt;a href=\"//s.weibo.com/weibo?q=%23%E5%AF%BC%E6%BC%94%E6%9B%BE%E4%BC%8F%E8%99%8E%23\" target=\"_blank\"&gt;#导演曾伏虎#&lt;/a&gt; ​​​ ...&lt;span class=\"expand\"&gt;展开&lt;/span&gt;", "customIcons": [], "ok": 1, "proof": "经查，该微博配发图片称 “绍兴城管5月11日上午十点左右，公然围攻抢有主人带有牵绳的狗”不实，@越城发布 已辟谣，犬主行为涉嫌违反《绍兴市文明行为促进条例》，在民警配合下，执法队员对该犬实施收容。详情https://weibo.com/5640807482/J1HuSkoOt，被投诉人言论构成“发布不实信息”。现根据《微博举报投诉操作细则》（http://service.account.weibo.com/roles/guiding）第19条，对被举报人处理如下：扣除信用积分2分。"}