{"visible": {"type": 0, "list_id": 0}, "created_at": "Fri May 03 20:59:05 +0800 2024", "id": 5030051294747119, "idstr": "5030051294747119", "mid": "5030051294747119", "mblogid": "OcBLPjUWr", "user": {"id": 1656737654, "idstr": "1656737654", "pc_new": 7, "screen_name": "现代快报", "profile_image_url": "https://tvax3.sinaimg.cn/crop.0.0.200.200.50/001O7v94ly8hkt56gw2d4j605k05kt8k02.jpg?KID=imgbed,tva&amp;Expires=1714806911&amp;ssig=mmYtnbEimt", "profile_url": "/u/1656737654", "verified": true, "verified_type": 3, "domain": "modernexpress", "weihao": "", "verified_type_ext": 0, "avatar_large": "https://tvax3.sinaimg.cn/crop.0.0.200.200.180/001O7v94ly8hkt56gw2d4j605k05kt8k02.jpg?KID=imgbed,tva&amp;Expires=1714806911&amp;ssig=8F0oLhkl77", "avatar_hd": "https://tvax3.sinaimg.cn/crop.0.0.200.200.1024/001O7v94ly8hkt56gw2d4j605k05kt8k02.jpg?KID=imgbed,tva&amp;Expires=1714806911&amp;ssig=uL4QsFHtGX", "follow_me": false, "following": false, "mbrank": 1, "mbtype": 12, "v_plus": 0, "planet_video": false, "icon_list": [{"type": "vip", "data": {"mbrank": 1, "mbtype": 12, "svip": 1, "vvip": 1}}, {"type": "icon", "data": {"value": "1", "icon_img": "https://h5.sinaimg.cn/upload/103/1892/2024/04/30/feed_icon_hangmu1_2x.png.png", "title": "为海军加油", "url": "https://s.weibo.com/weibo?q=%23003%23"}}]}, "can_edit": false, "text_raw": "#南京城事快报#【南京棉花堤渡口至旗杆渡口轮渡复航】近日，有网友反映，航拍南京眼时发现河西至江心洲轮渡复航了。5月3日，现代快报记者了解到，因江心洲旗杆渡口江堤消险工程完工，棉花堤渡口至旗杆渡口航线已经于5月1日复航。 http://t.cn/A6HPmdSl ​​​", "textLength": 233, "annotations": [{"oid": "1022:2309405030051296182613", "type": "article"}], "source": "微博 weibo.com", "favorited": false, "rid": "0_0_0_5067329744421287182_0_0_0", "cardid": "star_1624", "reads_count": 17109, "pic_ids": [], "pic_num": 0, "is_paid": false, "pic_bg_new": "http://vip.storage.weibo.com/feed_cover/star_1624_mobile_new.png?version=20240410", "mblog_vip_type": 0, "reposts_count": 1, "comments_count": 1, "attitudes_count": 3, "attitudes_status": 0, "isLongText": false, "mlevel": 0, "content_auth": 0, "is_show_bulletin": 2, "comment_manage_info": {"comment_permission_type": -1, "approval_comment_type": 0, "comment_sort_type": 0}, "share_repost_type": 0, "topic_struct": [{"title": "", "topic_url": "sinaweibo://searchall?containerid=231522&amp;q=%23%E5%8D%97%E4%BA%AC%E5%9F%8E%E4%BA%8B%E5%BF%AB%E6%8A%A5%23&amp;extparam=%23%E5%8D%97%E4%BA%AC%E5%9F%8E%E4%BA%8B%E5%BF%AB%E6%8A%A5%23", "topic_title": "南京城事快报", "actionlog": {"act_type": 1, "act_code": 300, "oid": "1022:2315226034b0284d053982e767b82c73ce4c72", "uuid": 4486802898420124, "cardid": "", "lcardid": "", "uicode": "", "luicode": "", "fid": "", "lfid": "", "ext": "mid:5030051294747119|rid:0_0_0_5067329744421287182_0_0_0|short_url:|long_url:|comment_id:|miduid:1656737654|rootmid:5030051294747119|rootuid:1656737654|authorid:|uuid:4486802898420124|is_ad_weibo:0"}}], "url_struct": [{"url_title": "南京棉花堤渡口至旗杆渡口轮渡复航", "url_type_pic": "https://h5.sinaimg.cn/upload/2015/09/25/3/timeline_card_small_article.png", "ori_url": "sinaweibo://articlebrowser?object_id=1022%3A2309405030051296182613&amp;url=https%3A%2F%2Fweibo.com%2Fttarticle%2Fx%2Fm%2Fshow%23%2Fid%3D2309405030051296182613%26_wb_client_%3D1&amp;extparam=lmid--5030051294747119", "page_id": "2309405030051296182613", "short_url": "http://t.cn/A6HPmdSl", "long_url": "https://weibo.com/ttarticle/p/show?id=2309405030051296182613", "url_type": 39, "result": false, "actionlog": {"act_type": 1, "act_code": 1423, "oid": "1022:2309405030051296182613", "uuid": 5030051295789342, "cardid": "", "lcardid": "", "uicode": "", "luicode": "", "fid": "", "lfid": "", "ext": "uid:1656737654|mid:5030051294747119|rootuid:1656737654|rootmid:5030051294747119|objectid:1022:2309405030051296182613||vuid:7774910775", "source": "article", "fromlog": ""}, "storage_type": "", "hide": 1, "object_type": "", "h5_target_url": "https://weibo.com/ttarticle/x/m/show#/id=2309405030051296182613&amp;_wb_client_=1", "need_save_obj": 0}], "title": {"text": "公开", "base_color": 1, "icon_url": "http://h5.sinaimg.cn/upload/2015/07/14/34/timeline_title_public.png"}, "mblogtype": 0, "showFeedRepost": false, "showFeedComment": false, "pictureViewerSign": false, "showPictureViewer": false, "rcList": [], "text": "&lt;a href=\"//s.weibo.com/weibo?q=%23%E5%8D%97%E4%BA%AC%E5%9F%8E%E4%BA%8B%E5%BF%AB%E6%8A%A5%23\" target=\"_blank\"&gt;#南京城事快报#&lt;/a&gt;【南京棉花堤渡口至旗杆渡口轮渡复航】近日，有网友反映，航拍南京眼时发现河西至江心洲轮渡复航了。5月3日，现代快报记者了解到，因江心洲旗杆渡口江堤消险工程完工，棉花堤渡口至旗杆渡口航线已经于5月1日复航。  ​​​", "customIcons": [], "page_info": {"type": "24", "page_id": "2309405030051296182613", "object_type": "article", "page_desc": "", "oid": 1656737654, "page_title": "@ 现代快报 ", "page_pic": "https://wx2.sinaimg.cn/large/001O7v94gy1hpcmijapryj60og0drmze02.jpg", "type_icon": "https://h5.sinaimg.cn/upload/2016/12/28/14/feed_headlines_icon_flash20161228_3.png", "page_url": "sinaweibo://articlebrowser?object_id=1022%3A2309405030051296182613&amp;url=https%3A%2F%2Fweibo.com%2Fttarticle%2Fx%2Fm%2Fshow%23%2Fid%3D2309405030051296182613%26_wb_client_%3D1&amp;extparam=lmid--5030051294747119", "object_id": "1022:2309405030051296182613", "author_id": 1656737654, "authorid": 1656737654, "content1": "南京棉花堤渡口至旗杆渡口轮渡复航", "content2": "", "content3": "现代快报", "preload": false, "content4": "", "user": {"id": "1656737654", "screen_name": " 现代快报", "profile_image_url": "https://tvax3.sinaimg.cn/crop.0.0.200.200.180/001O7v94ly8hkt56gw2d4j605k05kt8k02.jpg?KID=imgbed,tva&amp;Expires=1714806911&amp;ssig=8F0oLhkl77", "avatar_large": "https://tvax3.sinaimg.cn/crop.0.0.200.200.180/001O7v94ly8hkt56gw2d4j605k05kt8k02.jpg?KID=imgbed,tva&amp;Expires=1714806911&amp;ssig=8F0oLhkl77"}, "pic_info": {"pic_big": {"height": "333", "url": "https://wx2.sinaimg.cn/large/001O7v94gy1hpcmijapryj60og0drmze02.jpg", "width": "592"}}, "source_type": "article", "button_type": "follow", "button_follow_uid": "1656737654", "need_lmid": "1", "show_button": 1, "actionlog": {"act_type": 1, "act_code": 1423, "oid": "1022:2309405030051296182613", "uuid": 5030051295789342, "cardid": "", "lcardid": "", "uicode": "", "luicode": "", "fid": "", "lfid": "", "ext": "uid:1656737654|mid:5030051294747119|rootuid:1656737654|rootmid:5030051294747119|objectid:1022:2309405030051296182613||vuid:7774910775|analysis_card:page_info", "source": "article", "fromlog": ""}, "transition_pics": [{"pic_big": {"height": "333", "url": "https://wx2.sinaimg.cn/large/001O7v94gy1hpcmijapryj60og0drmze02.jpg", "width": "592"}}], "alpha_time": "700", "pause_time": "650", "buttons": [{"skip_format": 1, "type": "follow", "name": "加关注", "params": {"uid": "1656737654"}, "actionlog": {"act_code": 577, "oid": "2309405030051296182613", "cardid": "", "uicode": "", "fid": "", "ext": "mid:5030051294747119|rid:0_0_0_5067329744421287182_0_0_0|third_party_scheme_protocol:|action:加关注"}}]}, "ok": 1}